ezdsp/PARAMS.py
ezdsp/__init__.py
ezdsp/_demo_sig.py
ezdsp/_hilbert.py
ezdsp/_misc.py
ezdsp/_mne.py
ezdsp/_modulation_index.py
ezdsp/_pac.py
ezdsp/_psd.py
ezdsp/_resample.py
ezdsp/_transform.py
ezdsp/_utils.py
ezdsp/_wavelet.py
ezdsp/add_noise.py
ezdsp/filt.py
ezdsp/norm.py
ezdsp/ref.py
ezdsp/nn/_ChannelGainChanger.py
ezdsp/nn/_DropoutChannels.py
ezdsp/nn/_Filters.py
ezdsp/nn/_FreqGainChanger.py
ezdsp/nn/_Hilbert.py
ezdsp/nn/_ModulationIndex.py
ezdsp/nn/_PAC.py
ezdsp/nn/_PSD.py
ezdsp/nn/_Wavelet.py
ezdsp/nn/__init__.py
ezdsp-1.3.2.dist-info/LICENSE
ezdsp-1.3.2.dist-info/METADATA
ezdsp-1.3.2.dist-info/WHEEL
ezdsp-1.3.2.dist-info/top_level.txt
ezdsp-1.3.2.dist-info/RECORD
