Metadata-Version: 2.1
Name: ezdsp
Version: 1.3.2
Summary: Easy digital signal processing
Home-page: https://github.com/ywatanabe1989/ezdsp
Author: ywatanabe1989
Author-email: ywata1989@gmail.com
License: MIT
Keywords: numpytorch,pandas,LFP,EEG,MEG
Classifier: Programming Language :: Python :: 3
Classifier: License :: OSI Approved :: MIT License
Requires-Python: >=3.6
License-File: LICENSE
Requires-Dist: julius
Requires-Dist: matplotlib
Requires-Dist: mne
Requires-Dist: numpy
Requires-Dist: numpy-fn
Requires-Dist: pandas
Requires-Dist: ripple-detection
Requires-Dist: scipy
Requires-Dist: tensorpac
Requires-Dist: torch
Requires-Dist: torch-fn
Requires-Dist: torchaudio
Requires-Dist: torchsummary
Requires-Dist: mngs ==1.2.3
